rendering_minecraft/__init__.py
rendering_minecraft/rendering.py
rendering_minecraft-0.0.2.dist-info/LICENSE
rendering_minecraft-0.0.2.dist-info/METADATA
rendering_minecraft-0.0.2.dist-info/WHEEL
rendering_minecraft-0.0.2.dist-info/top_level.txt
rendering_minecraft-0.0.2.dist-info/RECORD
